capture/__init__.py
capture/_util.py
capture/client.py
capture/connector.py
vintecc_capture-0.1.0.dist-info/LICENSE
vintecc_capture-0.1.0.dist-info/METADATA
vintecc_capture-0.1.0.dist-info/WHEEL
vintecc_capture-0.1.0.dist-info/top_level.txt
vintecc_capture-0.1.0.dist-info/RECORD
